skill_homeassistant/__init__.py
skill_homeassistant/ha_client/__init__.py
skill_homeassistant/ha_client/constants.py
skill_homeassistant/ha_client/logic/__init__.py
skill_homeassistant/ha_client/logic/connector.py
skill_homeassistant/ha_client/logic/device.py
skill_homeassistant/ha_client/logic/utils.py
skill_homeassistant/locale/en-us/dialog/acknowledge.dialog
skill_homeassistant/locale/en-us/dialog/assist.dialog
skill_homeassistant/locale/en-us/dialog/assist.error.dialog
skill_homeassistant/locale/en-us/dialog/assist.not.understood.dialog
skill_homeassistant/locale/en-us/dialog/device.not.found.dialog
skill_homeassistant/locale/en-us/dialog/device.status.dialog
skill_homeassistant/locale/en-us/dialog/device.turned.off.dialog
skill_homeassistant/locale/en-us/dialog/device.turned.on.dialog
skill_homeassistant/locale/en-us/dialog/disable.dialog
skill_homeassistant/locale/en-us/dialog/enable.dialog
skill_homeassistant/locale/en-us/dialog/lights.current.brightness.dialog
skill_homeassistant/locale/en-us/dialog/lights.current.color.dialog
skill_homeassistant/locale/en-us/dialog/lights.status.not.available.dialog
skill_homeassistant/locale/en-us/dialog/no.parsed.device.dialog
skill_homeassistant/locale/en-us/dialog/vacuum.action.not.found.dialog
skill_homeassistant/locale/en-us/intents/assist.intent
skill_homeassistant/locale/en-us/intents/disable.intent
skill_homeassistant/locale/en-us/intents/enable.intent
skill_homeassistant/locale/en-us/intents/get.all.devices.intent
skill_homeassistant/locale/en-us/intents/lights.decrease.brightness.intent
skill_homeassistant/locale/en-us/intents/lights.get.brightness.intent
skill_homeassistant/locale/en-us/intents/lights.get.color.intent
skill_homeassistant/locale/en-us/intents/lights.increase.brightness.intent
skill_homeassistant/locale/en-us/intents/lights.set.brightness.intent
skill_homeassistant/locale/en-us/intents/lights.set.color.intent
skill_homeassistant/locale/en-us/intents/sensor.intent
skill_homeassistant-0.5.2.dist-info/METADATA
skill_homeassistant-0.5.2.dist-info/WHEEL
skill_homeassistant-0.5.2.dist-info/entry_points.txt
skill_homeassistant-0.5.2.dist-info/licenses/LICENSE
skill_homeassistant-0.5.2.dist-info/RECORD
