Metadata-Version: 2.4
Name: skill-homeassistant
Version: 0.5.2
Summary: A unified OVOS/Neon.AI Skill for Home Assistant.
License: Apache-2.0
License-File: LICENSE
Keywords: ovos,neon,home,assistant,voice,interface,skill,plugin
Author: Mike Gray
Author-email: mike@oscillatelabs.net
Requires-Python: >=3.9,<4.0
Classifier: License :: OSI Approved :: Apache Software License
Classifier: Programming Language :: Python :: 3
Classifier: Programming Language :: Python :: 3.9
Classifier: Programming Language :: Python :: 3.10
Classifier: Programming Language :: Python :: 3.11
Classifier: Programming Language :: Python :: 3.12
Classifier: Programming Language :: Python :: 3.13
Classifier: Programming Language :: Python :: 3.14
Provides-Extra: test
Requires-Dist: nested-lookup (>=0.2,<1.0)
Requires-Dist: ovos-bus-client (>=0.0.8)
Requires-Dist: ovos-config (>=0.0.5)
Requires-Dist: ovos-phal-plugin-oauth (>=0.0.3)
Requires-Dist: ovos-plugin-manager (>=0.0.23)
Requires-Dist: ovos-utils (>=0.0.27)
Requires-Dist: ovos-workshop (>=0.0.15)
Requires-Dist: setuptools (>=80.9.0,<81.0.0)
Requires-Dist: urllib3 (>=2.6.0)
Requires-Dist: webcolors (>=24.11.1)
